{"name":"build-javascript","namedChunkGroups":{"polyfill":{"name":"polyfill","assets":[{"name":"webpack-runtime-d15a1c48f51860e1aeae.js","size":3820},{"name":"polyfill-21fca359539f03306bcf.js","size":85029}],"filteredAssets":0,"assetsSize":88849,"filteredAuxiliaryAssets":2,"auxiliaryAssetsSize":226512},"app":{"name":"app","assets":[{"name":"webpack-runtime-d15a1c48f51860e1aeae.js","size":3820},{"name":"framework-6272cc5be474f89ad92a.js","size":205462},{"name":"app-1adf2b885dfbfffd213c.js","size":76937}],"filteredAssets":0,"assetsSize":286219,"filteredAuxiliaryAssets":3,"auxiliaryAssetsSize":838079},"component---src-pages-404-js":{"name":"component---src-pages-404-js","assets":[{"name":"component---src-pages-404-js-6cf0b1c9e96e47b2681b.js","size":798}],"filteredAssets":0,"assetsSize":798,"filteredAuxiliaryAssets":1,"auxiliaryAssetsSize":1747},"component---src-pages-index-js":{"name":"component---src-pages-index-js","assets":[{"name":"component---src-pages-index-js-6c1f205fa08e75e49ab8.js","size":171425}],"filteredAssets":0,"assetsSize":171425,"filteredAuxiliaryAssets":5,"auxiliaryAssetsSize":12452366}},"assetsByChunkName":{"polyfill":["webpack-runtime-d15a1c48f51860e1aeae.js","polyfill-21fca359539f03306bcf.js"],"app":["webpack-runtime-d15a1c48f51860e1aeae.js","framework-6272cc5be474f89ad92a.js","app-1adf2b885dfbfffd213c.js"],"component---src-pages-404-js":["component---src-pages-404-js-6cf0b1c9e96e47b2681b.js"],"component---src-pages-index-js":["component---src-pages-index-js-6c1f205fa08e75e49ab8.js"]},"childAssetsByChunkName":{}}